LICENSE
vu1_monitor/__init__.py
vu1_monitor/config/__init__.py
vu1_monitor/config/settings.py
vu1_monitor/dials/__init__.py
vu1_monitor/dials/client.py
vu1_monitor/exceptions/__init__.py
vu1_monitor/exceptions/dials.py
vu1_monitor/files/__init__.py
vu1_monitor/files/compression.py
vu1_monitor/files/lock.py
vu1_monitor/handlers/__init__.py
vu1_monitor/handlers/dials.py
vu1_monitor/handlers/process.py
vu1_monitor/logger/__init__.py
vu1_monitor/logger/logger.py
vu1_monitor/main.py
vu1_monitor/metrics/__init__.py
vu1_monitor/metrics/gpu.py
vu1_monitor/models/__init__.py
vu1_monitor/models/models.py
vu1_monitor/static/static.tgz
vu1_monitor-0.1.0.dist-info/LICENSE
vu1_monitor-0.1.0.dist-info/METADATA
vu1_monitor-0.1.0.dist-info/WHEEL
vu1_monitor-0.1.0.dist-info/entry_points.txt
vu1_monitor-0.1.0.dist-info/RECORD
