Metadata-Version: 2.1
Name: vu1-monitor
Version: 0.1.0
Summary: A CLI application for monitoring hardware with VU1-Dials
Home-page: https://github.com/christian-nickerson/vu1-monitor
License: Apache Licence 2.0
Keywords: vu1,vu1-dials,monitoring
Author: Christian Nickerson
Author-email: christian_nickerson@hotmail.com
Requires-Python: >=3.10,<4.0
Classifier: Environment :: Console
Classifier: License :: Other/Proprietary License
Classifier: Operating System :: OS Independent
Classifier: Programming Language :: Python :: 3
Classifier: Programming Language :: Python :: 3.10
Classifier: Programming Language :: Python :: 3.11
Classifier: Programming Language :: Python :: 3.12
Classifier: Topic :: System :: Monitoring
Requires-Dist: click (>=8.1.7,<9.0.0)
Requires-Dist: dynaconf (>=3.2.6,<4.0.0)
Requires-Dist: gputil (>=1.4.0,<2.0.0)
Requires-Dist: httpx (>=0.27.2,<0.28.0)
Requires-Dist: pillow (>=10.4.0,<11.0.0)
Requires-Dist: psutil (>=6.0.0,<7.0.0)
Requires-Dist: pyadl (>=0.1,<0.2)
Requires-Dist: setuptools (>=74.1.2,<75.0.0)
Project-URL: Repository, https://github.com/christian-nickerson/vu1-monitor
